funcenter/__init__.py
funcenter-1.4.1.dist-info/LICENSE
funcenter-1.4.1.dist-info/METADATA
funcenter-1.4.1.dist-info/WHEEL
funcenter-1.4.1.dist-info/RECORD
