Metadata-Version: 2.1
Name: funcenter
Version: 1.4.1
Summary: Some random functions I made... includes color formatting, text formatting, basic math, and most of all... dumb algorithms. Enjoy.
Home-page: https://uncenter.org/funcenter
License: MIT
Keywords: color,math,printing,simple
Author: uncenter
Author-email: contact@uncenter.org
Requires-Python: >=3.8,<4.0
Classifier: License :: OSI Approved :: MIT License
Classifier: Programming Language :: Python :: 3
Classifier: Programming Language :: Python :: 3.8
Classifier: Programming Language :: Python :: 3.9
Classifier: Programming Language :: Python :: 3.10
Classifier: Programming Language :: Python :: 3.11
Project-URL: Repository, https://github.com/intricateavocado/funcenter
